{"ids": {"1": "README.html", "2": "Delegating_Sub_Domains.html"}, "index": {"independently": [2], "want": [2], "only": [2], "same": [2], "standard": [2], "really": [1], "your": [1], "but": [2], "these": [2], "community": [1], "github": [1], "access": [2], "otherdomain": [2], "more": [2], "delegating": [2], "question": [2], "then": [2], "fqdn": [2], "approved": [1], "coms": [2], "powered": [1], "request": [1], "pull": [1], "add": [2], "markdown": [1], "correct": [2], "winxp5421": [1], "address": [2], "resolved": [2], "reply": [2], "welcome": [1], "behavior": [2], "idea": [1], "stop": [2], "tld": [2], "flow": [2], "using": [2], "live": [1], "over": [2], "where": [1], "what": [1, 2], "now": [2], "here": [1], "resolve": [2], "referred": [2], "which": [2], "created": [1], "with": [2, 1], "anyone": [1], "act": [2], "goes": [1], "enstate": [1], "ns2": [2], "can": [2, 1], "from": [2, 1], "delegate": [2], "return": [2], "written": [1], "are": [2], "get": [2], "response": [2], "actual": [2], "open": [1], "not": [2, 1], "under": [2], "full": [2], "converted": [1], "catch": [1], "records": [2], "collaborator": [1], "housed": [2], "also": [2], "how": [2], "honest": [1], "glue": [2], "sticky": [2], "one": [1], "servers": [2], "dns": [2], "connection": [2], "sure": [1], "order": [2], "this": [2, 1], "domain": [2], "main": [2], "resolves": [2], "html": [1], "never": [2], "manages": [2], "control": [2], "ns1": [2], "simply": [2], "others": [1], "submit": [1], "users": [1], "repo": [1], "post": [1], "source": [1], "something": [2], "com": [2, 1], "serves": [2], "somthing": [2], "vote": [1], "you": [2, 1], "environment": [2], "receive": [2], "governed": [1], "posts": [1], "reach": [2], "like": [1, 2], "completed": [2], "client": [2], "edit": [1], "top": [2], "denied": [1], "would": [1, 2], "content": [1], "record": [2], "underneath": [2], "pykwiki": [1], "must": [1, 2], "www": [2], "have": [2], "replay": [2], "level": [2], "sub": [2], "example": [2], "google": [2], "work": [2, 1], "behind": [1], "nothing": [2], "asks": [2], "root": [2], "static": [1], "wanted": [2], "loop": [2], "commonly": [2], "little": [2], "separate": [2], "adding": [2], "does": [2], "subdoman": [2], "file": [2], "than": [2], "name": [2], "probablynotahacker": [1], "will": [2, 1], "create": [1], "general": [1], "sub-domains": [2], "manage": [2], "wiki": [1], "https": [1], "domains": [2], "collaborators": [1], "peers": [1], "new": [2], "stuck": [2], "all": [1], "done": [2], "sub-domain": [2], "that": [2, 1], "127": [2], "for": [2], "issue": [1], "zone": [2], "things": [2], "via": [2], "simple": [1, 2], "please": [2], "ask": [2], "need": [2], "another": [2], "again": [2], "exactly": [2], "host": [2], "server": [2], "hotdam": [2]}, "tags": {"Server-Admin": [2], "README": [1]}, "updated": 1556325304}